[
    {
        "id": 278784,
        "name": "centercode1",
        "start": {
            "x": 296.1538461538461,
            "y": 188.47578195425174
        },
        "end": {
            "x": 315.38461538461536,
            "y": 389.2450127234825
        },
        "mode": "parent",
        "type": "center_code",
        "namingScheme": "number",
        "height": 200.76923076923072,
        "width": 19.230769230769234,
        "children": [
            {
                "id": 217344,
                "name": "0",
                "start": {
                    "x": 297.69230769230774,
                    "y": 211.2108259934645
                },
                "end": {
                    "x": 313.076923076923,
                    "y": 230.44159522423374
                },
                "mode": "child",
                "type": "option",
                "height": 19.230769230769226,
                "width": 15.384615384615387
            },
            {
                "id": 680704,
                "name": "1",
                "start": {
                    "x": 297.69230769230774,
                    "y": 229.67236445500296
                },
                "end": {
                    "x": 313.076923076923,
                    "y": 245.82621060884912
                },
                "mode": "child",
                "type": "option",
                "height": 16.15384615384616,
                "width": 15.384615384615387
            },
            {
                "id": 414720,
                "name": "2",
                "start": {
                    "x": 297.69230769230774,
                    "y": 246.5954413780799
                },
                "end": {
                    "x": 313.076923076923,
                    "y": 263.5185183011568
                },
                "mode": "child",
                "type": "option",
                "height": 16.923076923076906,
                "width": 15.384615384615387
            },
            {
                "id": 878592,
                "name": "3",
                "start": {
                    "x": 297.69230769230774,
                    "y": 264.28774907038763
                },
                "end": {
                    "x": 313.076923076923,
                    "y": 281.2108259934644
                },
                "mode": "child",
                "type": "option",
                "height": 16.923076923076906,
                "width": 15.384615384615387
            },
            {
                "id": 949504,
                "name": "4",
                "start": {
                    "x": 297.69230769230774,
                    "y": 281.2108259934644
                },
                "end": {
                    "x": 313.8461538461537,
                    "y": 299.6723644550029
                },
                "mode": "child",
                "type": "option",
                "height": 18.461538461538453,
                "width": 16.153846153846146
            },
            {
                "id": 838400,
                "name": "5",
                "start": {
                    "x": 297.69230769230774,
                    "y": 298.13390291654133
                },
                "end": {
                    "x": 314.61538461538464,
                    "y": 316.5954413780799
                },
                "mode": "child",
                "type": "option",
                "height": 18.46153846153851,
                "width": 16.92307692307692
            },
            {
                "id": 937216,
                "name": "6",
                "start": {
                    "x": 297.69230769230774,
                    "y": 316.5954413780799
                },
                "end": {
                    "x": 313.8461538461537,
                    "y": 331.98005676269526
                },
                "mode": "child",
                "type": "option",
                "height": 15.384615384615358,
                "width": 16.153846153846146
            },
            {
                "id": 102144,
                "name": "7",
                "start": {
                    "x": 296.9230769230768,
                    "y": 332.749287531926
                },
                "end": {
                    "x": 313.076923076923,
                    "y": 349.6723644550029
                },
                "mode": "child",
                "type": "option",
                "height": 16.923076923076906,
                "width": 16.153846153846153
            },
            {
                "id": 306432,
                "name": "8",
                "start": {
                    "x": 296.9230769230768,
                    "y": 350.4415952242337
                },
                "end": {
                    "x": 313.8461538461537,
                    "y": 368.13390291654133
                },
                "mode": "child",
                "type": "option",
                "height": 17.69230769230768,
                "width": 16.923076923076913
            },
            {
                "id": 179456,
                "name": "9",
                "start": {
                    "x": 296.9230769230768,
                    "y": 368.13390291654133
                },
                "end": {
                    "x": 313.076923076923,
                    "y": 386.5954413780798
                },
                "mode": "child",
                "type": "option",
                "height": 18.461538461538453,
                "width": 16.153846153846153
            }
        ],
        "isOpen": false
    },
    {
        "id": 752192,
        "name": "centercode2",
        "start": {
            "x": 328.1538461538462,
            "y": 188.5527050311748
        },
        "end": {
            "x": 347.38461538461536,
            "y": 389.3219358004056
        },
        "mode": "parent",
        "type": "center_code",
        "namingScheme": "number",
        "height": 200.76923076923072,
        "width": 19.230769230769234,
        "children": [
            {
                "id": 945984,
                "name": "0",
                "start": {
                    "x": 329.69230769230774,
                    "y": 211.28774907038758
                },
                "end": {
                    "x": 345.076923076923,
                    "y": 230.5185183011568
                },
                "mode": "child",
                "type": "option",
                "height": 19.230769230769226,
                "width": 15.384615384615387
            },
            {
                "id": 293184,
                "name": "1",
                "start": {
                    "x": 329.69230769230774,
                    "y": 229.74928753192603
                },
                "end": {
                    "x": 345.076923076923,
                    "y": 245.90313368577222
                },
                "mode": "child",
                "type": "option",
                "height": 16.15384615384616,
                "width": 15.384615384615387
            },
            {
                "id": 940352,
                "name": "2",
                "start": {
                    "x": 329.69230769230774,
                    "y": 246.67236445500293
                },
                "end": {
                    "x": 345.076923076923,
                    "y": 263.5954413780799
                },
                "mode": "child",
                "type": "option",
                "height": 16.923076923076906,
                "width": 15.384615384615387
            },
            {
                "id": 225344,
                "name": "3",
                "start": {
                    "x": 329.69230769230774,
                    "y": 264.3646721473106
                },
                "end": {
                    "x": 345.076923076923,
                    "y": 281.28774907038763
                },
                "mode": "child",
                "type": "option",
                "height": 16.923076923076906,
                "width": 15.384615384615387
            },
            {
                "id": 701760,
                "name": "4",
                "start": {
                    "x": 329.69230769230774,
                    "y": 281.28774907038763
                },
                "end": {
                    "x": 345.8461538461537,
                    "y": 299.7492875319261
                },
                "mode": "child",
                "type": "option",
                "height": 18.461538461538453,
                "width": 16.153846153846146
            },
            {
                "id": 745536,
                "name": "5",
                "start": {
                    "x": 329.69230769230774,
                    "y": 298.21082599346454
                },
                "end": {
                    "x": 346.61538461538464,
                    "y": 316.672364455003
                },
                "mode": "child",
                "type": "option",
                "height": 18.46153846153851,
                "width": 16.92307692307692
            },
            {
                "id": 715072,
                "name": "6",
                "start": {
                    "x": 329.69230769230774,
                    "y": 316.672364455003
                },
                "end": {
                    "x": 345.8461538461537,
                    "y": 332.05697983961835
                },
                "mode": "child",
                "type": "option",
                "height": 15.384615384615358,
                "width": 16.153846153846146
            },
            {
                "id": 202304,
                "name": "7",
                "start": {
                    "x": 328.9230769230769,
                    "y": 332.8262106088492
                },
                "end": {
                    "x": 345.076923076923,
                    "y": 349.7492875319261
                },
                "mode": "child",
                "type": "option",
                "height": 16.923076923076906,
                "width": 16.153846153846153
            },
            {
                "id": 525376,
                "name": "8",
                "start": {
                    "x": 328.9230769230769,
                    "y": 350.5185183011568
                },
                "end": {
                    "x": 345.8461538461537,
                    "y": 368.21082599346454
                },
                "mode": "child",
                "type": "option",
                "height": 17.69230769230768,
                "width": 16.923076923076913
            },
            {
                "id": 558912,
                "name": "9",
                "start": {
                    "x": 328.9230769230769,
                    "y": 368.21082599346454
                },
                "end": {
                    "x": 345.076923076923,
                    "y": 386.672364455003
                },
                "mode": "child",
                "type": "option",
                "height": 18.461538461538453,
                "width": 16.153846153846153
            }
        ],
        "isOpen": false
    },
    {
        "id": 896448,
        "name": "centercode3",
        "start": {
            "x": 360.8461538461538,
            "y": 187.9373204157902
        },
        "end": {
            "x": 380.0769230769231,
            "y": 388.70655118502094
        },
        "mode": "parent",
        "type": "center_code",
        "namingScheme": "number",
        "height": 200.76923076923072,
        "width": 19.230769230769234,
        "children": [
            {
                "id": 898752,
                "name": "0",
                "start": {
                    "x": 362.38461538461536,
                    "y": 210.67236445500296
                },
                "end": {
                    "x": 377.7692307692308,
                    "y": 229.9031336857722
                },
                "mode": "child",
                "type": "option",
                "height": 19.230769230769226,
                "width": 15.384615384615387
            },
            {
                "id": 363200,
                "name": "1",
                "start": {
                    "x": 362.38461538461536,
                    "y": 229.13390291654142
                },
                "end": {
                    "x": 377.7692307692308,
                    "y": 245.28774907038758
                },
                "mode": "child",
                "type": "option",
                "height": 16.15384615384616,
                "width": 15.384615384615387
            },
            {
                "id": 353984,
                "name": "2",
                "start": {
                    "x": 362.38461538461536,
                    "y": 246.05697983961835
                },
                "end": {
                    "x": 377.7692307692308,
                    "y": 262.98005676269526
                },
                "mode": "child",
                "type": "option",
                "height": 16.923076923076906,
                "width": 15.384615384615387
            },
            {
                "id": 508352,
                "name": "3",
                "start": {
                    "x": 362.38461538461536,
                    "y": 263.74928753192603
                },
                "end": {
                    "x": 377.7692307692308,
                    "y": 280.67236445500293
                },
                "mode": "child",
                "type": "option",
                "height": 16.923076923076906,
                "width": 15.384615384615387
            },
            {
                "id": 132032,
                "name": "4",
                "start": {
                    "x": 362.38461538461536,
                    "y": 280.67236445500293
                },
                "end": {
                    "x": 378.53846153846155,
                    "y": 299.1339029165414
                },
                "mode": "child",
                "type": "option",
                "height": 18.461538461538453,
                "width": 16.153846153846146
            },
            {
                "id": 776640,
                "name": "5",
                "start": {
                    "x": 362.38461538461536,
                    "y": 297.59544137807984
                },
                "end": {
                    "x": 379.30769230769226,
                    "y": 316.05697983961835
                },
                "mode": "child",
                "type": "option",
                "height": 18.46153846153851,
                "width": 16.92307692307692
            },
            {
                "id": 535232,
                "name": "6",
                "start": {
                    "x": 362.38461538461536,
                    "y": 316.05697983961835
                },
                "end": {
                    "x": 378.53846153846155,
                    "y": 331.4415952242337
                },
                "mode": "child",
                "type": "option",
                "height": 15.384615384615358,
                "width": 16.153846153846146
            },
            {
                "id": 273600,
                "name": "7",
                "start": {
                    "x": 361.61538461538464,
                    "y": 332.2108259934645
                },
                "end": {
                    "x": 377.7692307692308,
                    "y": 349.1339029165414
                },
                "mode": "child",
                "type": "option",
                "height": 16.923076923076906,
                "width": 16.153846153846153
            },
            {
                "id": 530880,
                "name": "8",
                "start": {
                    "x": 361.61538461538464,
                    "y": 349.90313368577216
                },
                "end": {
                    "x": 378.53846153846155,
                    "y": 367.59544137807984
                },
                "mode": "child",
                "type": "option",
                "height": 17.69230769230768,
                "width": 16.923076923076913
            },
            {
                "id": 796608,
                "name": "9",
                "start": {
                    "x": 361.61538461538464,
                    "y": 367.59544137807984
                },
                "end": {
                    "x": 377.7692307692308,
                    "y": 386.0569798396183
                },
                "mode": "child",
                "type": "option",
                "height": 18.461538461538453,
                "width": 16.153846153846153
            }
        ],
        "isOpen": true
    },
    {
        "id": 875392,
        "name": "centercode4",
        "start": {
            "x": 393.8461538461538,
            "y": 187.9373204157902
        },
        "end": {
            "x": 413.0769230769231,
            "y": 388.70655118502094
        },
        "mode": "parent",
        "type": "center_code",
        "namingScheme": "number",
        "height": 200.76923076923072,
        "width": 19.230769230769234,
        "children": [
            {
                "id": 577664,
                "name": "0",
                "start": {
                    "x": 395.38461538461536,
                    "y": 210.67236445500296
                },
                "end": {
                    "x": 410.7692307692308,
                    "y": 229.9031336857722
                },
                "mode": "child",
                "type": "option",
                "height": 19.230769230769226,
                "width": 15.384615384615387
            },
            {
                "id": 368000,
                "name": "1",
                "start": {
                    "x": 395.38461538461536,
                    "y": 229.13390291654142
                },
                "end": {
                    "x": 410.7692307692308,
                    "y": 245.28774907038758
                },
                "mode": "child",
                "type": "option",
                "height": 16.15384615384616,
                "width": 15.384615384615387
            },
            {
                "id": 443264,
                "name": "2",
                "start": {
                    "x": 395.38461538461536,
                    "y": 246.05697983961835
                },
                "end": {
                    "x": 410.7692307692308,
                    "y": 262.98005676269526
                },
                "mode": "child",
                "type": "option",
                "height": 16.923076923076906,
                "width": 15.384615384615387
            },
            {
                "id": 257920,
                "name": "3",
                "start": {
                    "x": 395.38461538461536,
                    "y": 263.74928753192603
                },
                "end": {
                    "x": 410.7692307692308,
                    "y": 280.67236445500293
                },
                "mode": "child",
                "type": "option",
                "height": 16.923076923076906,
                "width": 15.384615384615387
            },
            {
                "id": 609408,
                "name": "4",
                "start": {
                    "x": 395.38461538461536,
                    "y": 280.67236445500293
                },
                "end": {
                    "x": 411.53846153846155,
                    "y": 299.1339029165414
                },
                "mode": "child",
                "type": "option",
                "height": 18.461538461538453,
                "width": 16.153846153846146
            },
            {
                "id": 778368,
                "name": "5",
                "start": {
                    "x": 395.38461538461536,
                    "y": 297.59544137807984
                },
                "end": {
                    "x": 412.30769230769226,
                    "y": 316.05697983961835
                },
                "mode": "child",
                "type": "option",
                "height": 18.46153846153851,
                "width": 16.92307692307692
            },
            {
                "id": 819328,
                "name": "6",
                "start": {
                    "x": 395.38461538461536,
                    "y": 316.05697983961835
                },
                "end": {
                    "x": 411.53846153846155,
                    "y": 331.4415952242337
                },
                "mode": "child",
                "type": "option",
                "height": 15.384615384615358,
                "width": 16.153846153846146
            },
            {
                "id": 320384,
                "name": "7",
                "start": {
                    "x": 394.61538461538464,
                    "y": 332.2108259934645
                },
                "end": {
                    "x": 410.7692307692308,
                    "y": 349.1339029165414
                },
                "mode": "child",
                "type": "option",
                "height": 16.923076923076906,
                "width": 16.153846153846153
            },
            {
                "id": 921216,
                "name": "8",
                "start": {
                    "x": 394.61538461538464,
                    "y": 349.90313368577216
                },
                "end": {
                    "x": 411.53846153846155,
                    "y": 367.59544137807984
                },
                "mode": "child",
                "type": "option",
                "height": 17.69230769230768,
                "width": 16.923076923076913
            },
            {
                "id": 944256,
                "name": "9",
                "start": {
                    "x": 394.61538461538464,
                    "y": 367.59544137807984
                },
                "end": {
                    "x": 410.7692307692308,
                    "y": 386.0569798396183
                },
                "mode": "child",
                "type": "option",
                "height": 18.461538461538453,
                "width": 16.153846153846153
            }
        ],
        "isOpen": true
    }
]